src/102053010.py
src/__init__.py
src/topsis.py
102053010-0.0.1.dist-info/LICENSE.txt
102053010-0.0.1.dist-info/METADATA
102053010-0.0.1.dist-info/WHEEL
102053010-0.0.1.dist-info/top_level.txt
102053010-0.0.1.dist-info/RECORD
